EDALIB/__init__.py
buildlytics_test_3-0.0.3.dist-info/LICENSE.txt
buildlytics_test_3-0.0.3.dist-info/METADATA
buildlytics_test_3-0.0.3.dist-info/WHEEL
buildlytics_test_3-0.0.3.dist-info/top_level.txt
buildlytics_test_3-0.0.3.dist-info/RECORD
