Metadata-Version: 2.1
Name: buildlytics-test-3
Version: 0.0.3
Summary: EDA Package Test 
Home-page: UNKNOWN
Author: UNKNOWN
Author-email: UNKNOWN
License: MIT
Platform: any
Classifier: Programming Language :: Python
Classifier: Operating System :: OS Independent
Classifier: Intended Audience :: Science/Research
Classifier: Topic :: Scientific/Engineering
Requires-Dist: numpy
Requires-Dist: pandas
Requires-Dist: seaborn
